splunk_kvstore_cli.py
splunk_kvstore_cli-1.1.0.dist-info/LICENSE
splunk_kvstore_cli-1.1.0.dist-info/METADATA
splunk_kvstore_cli-1.1.0.dist-info/WHEEL
splunk_kvstore_cli-1.1.0.dist-info/entry_points.txt
splunk_kvstore_cli-1.1.0.dist-info/top_level.txt
splunk_kvstore_cli-1.1.0.dist-info/RECORD
